{"type":"FeatureCollection","features":[{"type":"Feature","id":"STADTKASSEOGD.327","geometry":{"type":"Point","coordinates":[16.34704265,48.20284971]},"geometry_name":"SHAPE","properties":{"OBJECTID":327,"BEZIRK":7,"ADRESSE":"07., Hermanngasse 24-26","WEBLINK1":"https://www.wien.gv.at/advuew/internet/AdvPrSrv.asp?Layout=stelle&Type=K&stellecd=2001061415230256&STELLE=Y","BEZEICHNUNG":"Stadtkasse 7., Kassenstelle der BA 34","SE_ANNO_CAD_DATA":null}},{"type":"Feature","id":"STADTKASSEOGD.328","geometry":{"type":"Point","coordinates":[16.37401358,48.17879199]},"geometry_name":"SHAPE","properties":{"OBJECTID":328,"BEZIRK":10,"ADRESSE":"10., Laxenburger Straße 43-45","WEBLINK1":"https://www.wien.gv.at/advuew/internet/AdvPrSrv.asp?Layout=stelle&Type=K&stellecd=2001061415230256&STELLE=Y","BEZEICHNUNG":"Stadtkasse 10., Kassenstelle im MBA 10","SE_ANNO_CAD_DATA":null}},{"type":"Feature","id":"STADTKASSEOGD.329","geometry":{"type":"Point","coordinates":[16.41367098,48.17558793]},"geometry_name":"SHAPE","properties":{"OBJECTID":329,"BEZIRK":11,"ADRESSE":"11., Enkplatz 2","WEBLINK1":"https://www.wien.gv.at/advuew/internet/AdvPrSrv.asp?Layout=stelle&Type=K&stellecd=2001061415230256&STELLE=Y","BEZEICHNUNG":"Stadtkasse 11., Kassenstelle im MBA 11 - Front Office","SE_ANNO_CAD_DATA":null}},{"type":"Feature","id":"STADTKASSEOGD.330","geometry":{"type":"Point","coordinates":[16.32916328,48.18311847]},"geometry_name":"SHAPE","properties":{"OBJECTID":330,"BEZIRK":12,"ADRESSE":"12., Schönbrunner Straße 259","WEBLINK1":"https://www.wien.gv.at/advuew/internet/AdvPrSrv.asp?Layout=stelle&Type=K&stellecd=2001061415230256&STELLE=Y","BEZEICHNUNG":"Stadtkasse 12., Kassenstelle 12 im MBA 12","SE_ANNO_CAD_DATA":null}},{"type":"Feature","id":"STADTKASSEOGD.331","geometry":{"type":"Point","coordinates":[16.29975455,48.18824079]},"geometry_name":"SHAPE","properties":{"OBJECTID":331,"BEZIRK":13,"ADRESSE":"13., Dommayergasse 12","WEBLINK1":"https://www.wien.gv.at/advuew/internet/AdvPrSrv.asp?Layout=stelle&Type=K&stellecd=2001061415230256&STELLE=Y","BEZEICHNUNG":"Stadtkasse 13., Kassenstelle im MBA 13/14","SE_ANNO_CAD_DATA":null}},{"type":"Feature","id":"STADTKASSEOGD.332","geometry":{"type":"Point","coordinates":[16.33410387,48.19412056]},"geometry_name":"SHAPE","properties":{"OBJECTID":332,"BEZIRK":15,"ADRESSE":"15., Gasgasse 8-10","WEBLINK1":"https://www.wien.gv.at/advuew/internet/AdvPrSrv.asp?Layout=stelle&Type=K&stellecd=2001061415230256&STELLE=Y","BEZEICHNUNG":"Stadtkasse 15., Kassenstelle im MBA 15 - Front Office","SE_ANNO_CAD_DATA":null}},{"type":"Feature","id":"STADTKASSEOGD.333","geometry":{"type":"Point","coordinates":[16.32727634,48.20927815]},"geometry_name":"SHAPE","properties":{"OBJECTID":333,"BEZIRK":16,"ADRESSE":"16., Richard-Wagner-Platz 19","WEBLINK1":"https://www.wien.gv.at/advuew/internet/AdvPrSrv.asp?Layout=stelle&Type=K&stellecd=2001061415230256&STELLE=Y","BEZEICHNUNG":"Stadtkasse 16., Kassenstelle im MBA 16 - Front Office","SE_ANNO_CAD_DATA":null}},{"type":"Feature","id":"STADTKASSEOGD.334","geometry":{"type":"Point","coordinates":[16.33200226,48.21829708]},"geometry_name":"SHAPE","properties":{"OBJECTID":334,"BEZIRK":17,"ADRESSE":"17., Elterleinplatz 14","WEBLINK1":"https://www.wien.gv.at/advuew/internet/AdvPrSrv.asp?Layout=stelle&Type=K&stellecd=2001061415230256&STELLE=Y","BEZEICHNUNG":"Stadtkasse 17., Kassenstelle im MBA 17","SE_ANNO_CAD_DATA":null}},{"type":"Feature","id":"STADTKASSEOGD.335","geometry":{"type":"Point","coordinates":[16.34242582,48.22684654]},"geometry_name":"SHAPE","properties":{"OBJECTID":335,"BEZIRK":18,"ADRESSE":"18., Martinstraße 100","WEBLINK1":"https://www.wien.gv.at/advuew/internet/AdvPrSrv.asp?Layout=stelle&Type=K&stellecd=2001061415230256&STELLE=Y","BEZEICHNUNG":"Stadtkasse 18., Kassenstelle im MBA 18","SE_ANNO_CAD_DATA":null}},{"type":"Feature","id":"STADTKASSEOGD.336","geometry":{"type":"Point","coordinates":[16.37002359,48.2520806]},"geometry_name":"SHAPE","properties":{"OBJECTID":336,"BEZIRK":19,"ADRESSE":"19., Muthgasse 62","WEBLINK1":"https://www.wien.gv.at/advuew/internet/AdvPrSrv.asp?Layout=stelle&Type=K&stellecd=2001061415230256&STELLE=Y","BEZEICHNUNG":"Stadtkasse 19., Kassenstelle des Erhebungs- und Vollstreckungsdienstes","SE_ANNO_CAD_DATA":null}},{"type":"Feature","id":"STADTKASSEOGD.337","geometry":{"type":"Point","coordinates":[16.37101852,48.23297405]},"geometry_name":"SHAPE","properties":{"OBJECTID":337,"BEZIRK":20,"ADRESSE":"20., Brigittaplatz 10","WEBLINK1":"https://www.wien.gv.at/advuew/internet/AdvPrSrv.asp?Layout=stelle&Type=K&stellecd=2001061415230256&STELLE=Y","BEZEICHNUNG":"Stadtkasse 20., Kassenstelle im MBA 20","SE_ANNO_CAD_DATA":null}},{"type":"Feature","id":"STADTKASSEOGD.338","geometry":{"type":"Point","coordinates":[16.39729541,48.2577655]},"geometry_name":"SHAPE","properties":{"OBJECTID":338,"BEZIRK":21,"ADRESSE":"21., Am Spitz 1","WEBLINK1":"https://www.wien.gv.at/advuew/internet/AdvPrSrv.asp?Layout=stelle&Type=K&stellecd=2001061415230256&STELLE=Y","BEZEICHNUNG":"Stadtkasse 21., Kassenstelle im MBA 21","SE_ANNO_CAD_DATA":null}},{"type":"Feature","id":"STADTKASSEOGD.339","geometry":{"type":"Point","coordinates":[16.43778168,48.24101163]},"geometry_name":"SHAPE","properties":{"OBJECTID":339,"BEZIRK":22,"ADRESSE":"22., Schrödingerplatz 1","WEBLINK1":"https://www.wien.gv.at/advuew/internet/AdvPrSrv.asp?Layout=stelle&Type=K&stellecd=2001061415230256&STELLE=Y","BEZEICHNUNG":"Stadtkasse 22., Kassenstelle im MBA 22 - Front Office","SE_ANNO_CAD_DATA":null}},{"type":"Feature","id":"STADTKASSEOGD.340","geometry":{"type":"Point","coordinates":[16.28215297,48.13486362]},"geometry_name":"SHAPE","properties":{"OBJECTID":340,"BEZIRK":23,"ADRESSE":"23., Perchtoldsdorfer Straße 2","WEBLINK1":"https://www.wien.gv.at/advuew/internet/AdvPrSrv.asp?Layout=stelle&Type=K&stellecd=2001061415230256&STELLE=Y","BEZEICHNUNG":"Stadtkasse 23., Kassenstelle im MBA 23 - Front Office","SE_ANNO_CAD_DATA":null}},{"type":"Feature","id":"STADTKASSEOGD.321","geometry":{"type":"Point","coordinates":[16.35729756,48.21083902]},"geometry_name":"SHAPE","properties":{"OBJECTID":321,"BEZIRK":8,"ADRESSE":"08., Friedrich-Schmidt-Platz 1","WEBLINK1":"https://www.wien.gv.at/advuew/internet/AdvPrSrv.asp?Layout=stelle&Type=K&stellecd=2001061415230256&STELLE=Y","BEZEICHNUNG":"Stadthauptkasse","SE_ANNO_CAD_DATA":null}},{"type":"Feature","id":"STADTKASSEOGD.322","geometry":{"type":"Point","coordinates":[16.37102527,48.21180622]},"geometry_name":"SHAPE","properties":{"OBJECTID":322,"BEZIRK":1,"ADRESSE":"01., Wipplingerstraße 8","WEBLINK1":"https://www.wien.gv.at/advuew/internet/AdvPrSrv.asp?Layout=stelle&Type=K&stellecd=2001061415230256&STELLE=Y","BEZEICHNUNG":"Stadtkasse 1.,  Kassenstelle im MBA 1 - Front Office","SE_ANNO_CAD_DATA":null}},{"type":"Feature","id":"STADTKASSEOGD.323","geometry":{"type":"Point","coordinates":[16.37972346,48.21651219]},"geometry_name":"SHAPE","properties":{"OBJECTID":323,"BEZIRK":2,"ADRESSE":"02., Karmelitergasse 9","WEBLINK1":"https://www.wien.gv.at/advuew/internet/AdvPrSrv.asp?Layout=stelle&Type=K&stellecd=2001061415230256&STELLE=Y","BEZEICHNUNG":"Stadtkasse 2.,  Kassenstelle im MBA 2","SE_ANNO_CAD_DATA":null}},{"type":"Feature","id":"STADTKASSEOGD.324","geometry":{"type":"Point","coordinates":[16.38866008,48.20133617]},"geometry_name":"SHAPE","properties":{"OBJECTID":324,"BEZIRK":3,"ADRESSE":"03., Karl-Borromäus-Platz 3","WEBLINK1":"https://www.wien.gv.at/advuew/internet/AdvPrSrv.asp?Layout=stelle&Type=K&stellecd=2001061415230256&STELLE=Y","BEZEICHNUNG":"Stadtkasse 3., Kassenstelle im MBA 3 - Front Office","SE_ANNO_CAD_DATA":null}},{"type":"Feature","id":"STADTKASSEOGD.325","geometry":{"type":"Point","coordinates":[16.41098876,48.19394512]},"geometry_name":"SHAPE","properties":{"OBJECTID":325,"BEZIRK":3,"ADRESSE":"03., Thomas-Klestil-Platz 8","WEBLINK1":"https://www.wien.gv.at/advuew/internet/AdvPrSrv.asp?Layout=stelle&Type=K&stellecd=2001061415230256&STELLE=Y","BEZEICHNUNG":"Stadtkasse 3., Kassenstelle der BA 14","SE_ANNO_CAD_DATA":null}},{"type":"Feature","id":"STADTKASSEOGD.326","geometry":{"type":"Point","coordinates":[16.35410162,48.19099555]},"geometry_name":"SHAPE","properties":{"OBJECTID":326,"BEZIRK":5,"ADRESSE":"05., Rechte Wienzeile 105","WEBLINK1":"https://www.wien.gv.at/advuew/internet/AdvPrSrv.asp?Layout=stelle&Type=K&stellecd=2001061415230256&STELLE=Y","BEZEICHNUNG":"Stadtkasse 5., Kassenstelle im MBA 4/5 - Front Office","SE_ANNO_CAD_DATA":null}}],"totalFeatures":20,"numberMatched":20,"numberReturned":20,"timeStamp":"2026-05-03T16:51:38.362Z","crs":{"type":"name","properties":{"name":"urn:ogc:def:crs:EPSG::4326"}}}